pwl_writer/__init__.py
pwl_writer/pwl_writer.py
pwl_writer-1.2.0.dist-info/LICENSE
pwl_writer-1.2.0.dist-info/WHEEL
pwl_writer-1.2.0.dist-info/METADATA
pwl_writer-1.2.0.dist-info/RECORD
