Metadata-Version: 2.1
Name: pwl_writer
Version: 1.2.0
Summary: Package to generate PWL files incrementally using little 'events' like rectangular pulses and exponential rising or falling edges.
Author-email: "Victor Sabiá P. Carpes" <victorscarpes@gmail.com>
Requires-Python: >=3.6.6
Classifier: License :: OSI Approved :: MIT License
Requires-Dist: numpy >= 1.13
Requires-Dist: pycco ; extra == "doc"
Requires-Dist: matplotlib ; extra == "plot"
Project-URL: Documentation, https://htmlpreview.github.io/?https://github.com/victorscarpes/pwl_writer/blob/main/docs/pwl_writer.html
Project-URL: Source, https://github.com/victorscarpes/pwl_writer
Provides-Extra: doc
Provides-Extra: plot
